tastytrade_sdk/__init__.py
tastytrade_sdk/api.py
tastytrade_sdk/config.py
tastytrade_sdk/exceptions.py
tastytrade_sdk/market_data/__init__.py
tastytrade_sdk/market_data/market_data.py
tastytrade_sdk/market_data/streamer_symbol_translation.py
tastytrade_sdk/market_data/subscription.py
tastytrade_sdk/tastytrade.py
tastytrade_sdk-1.2.0.dist-info/LICENSE
tastytrade_sdk-1.2.0.dist-info/METADATA
tastytrade_sdk-1.2.0.dist-info/WHEEL
tastytrade_sdk-1.2.0.dist-info/RECORD
