Metadata-Version: 2.1
Name: tastytrade-sdk
Version: 1.2.0
Summary: A python wrapper around the tastytrade open API
License: MIT
Author: Aaron Mamparo
Author-email: aaronmamparo@gmail.com
Requires-Python: >=3.8,<4.0
Classifier: License :: OSI Approved :: MIT License
Classifier: Programming Language :: Python :: 3
Classifier: Programming Language :: Python :: 3.8
Classifier: Programming Language :: Python :: 3.9
Classifier: Programming Language :: Python :: 3.10
Classifier: Programming Language :: Python :: 3.11
Classifier: Programming Language :: Python :: 3.12
Requires-Dist: bidict (>=0.22.1,<0.23.0)
Requires-Dist: injector (>=0.20.1,<0.21.0)
Requires-Dist: requests (>=2.31.0,<3.0.0)
Requires-Dist: strenum (>=0.4.15,<0.5.0)
Requires-Dist: ujson (>=5.8.0,<6.0.0)
Requires-Dist: websockets (>=11.0.3,<12.0.0)
